glitter_sdk/.gitignore
glitter_sdk/__init__.py
glitter_sdk/client/__init__.py
glitter_sdk/client/lcd/__init__.py
glitter_sdk/client/lcd/api/__init__.py
glitter_sdk/client/lcd/api/_base.py
glitter_sdk/client/lcd/api/auth.py
glitter_sdk/client/lcd/api/authz.py
glitter_sdk/client/lcd/api/bank.py
glitter_sdk/client/lcd/api/distribution.py
glitter_sdk/client/lcd/api/feegrant.py
glitter_sdk/client/lcd/api/gov.py
glitter_sdk/client/lcd/api/ibc.py
glitter_sdk/client/lcd/api/ibc_transfer.py
glitter_sdk/client/lcd/api/mint.py
glitter_sdk/client/lcd/api/slashing.py
glitter_sdk/client/lcd/api/staking.py
glitter_sdk/client/lcd/api/tendermint.py
glitter_sdk/client/lcd/api/tx.py
glitter_sdk/client/lcd/api/wasm.py
glitter_sdk/client/lcd/constants/CLIENT.py
glitter_sdk/client/lcd/constants/__init__.py
glitter_sdk/client/lcd/dataset.py
glitter_sdk/client/lcd/lcdclient.py
glitter_sdk/client/lcd/lcdutils.py
glitter_sdk/client/lcd/params.py
glitter_sdk/client/lcd/query_node.py
glitter_sdk/connection.py
glitter_sdk/core/__init__.py
glitter_sdk/core/auth/__init__.py
glitter_sdk/core/auth/data/__init__.py
glitter_sdk/core/auth/data/account.py
glitter_sdk/core/auth/data/base_account.py
glitter_sdk/core/auth/data/base_vesting_account.py
glitter_sdk/core/auth/data/continuous_vesting_account.py
glitter_sdk/core/auth/data/delayed_vesting_account.py
glitter_sdk/core/auth/data/eth_account.py
glitter_sdk/core/auth/data/periodic_vesting_account.py
glitter_sdk/core/auth/msgs/__init__.py
glitter_sdk/core/auth/msgs/msg_create_periodic_vesting_account.py
glitter_sdk/core/auth/msgs/msg_create_vesting_account.py
glitter_sdk/core/auth/msgs/msg_donate_all_vesting_tokens.py
glitter_sdk/core/authz/__init__.py
glitter_sdk/core/authz/data.py
glitter_sdk/core/authz/msgs.py
glitter_sdk/core/bank/__init__.py
glitter_sdk/core/bank/msgs.py
glitter_sdk/core/bech32.py
glitter_sdk/core/block.py
glitter_sdk/core/broadcast.py
glitter_sdk/core/coin.py
glitter_sdk/core/coins.py
glitter_sdk/core/compact_bit_array.py
glitter_sdk-2.0.0.dist-info/LICENSE
glitter_sdk-2.0.0.dist-info/METADATA
glitter_sdk-2.0.0.dist-info/WHEEL
glitter_sdk-2.0.0.dist-info/RECORD
