Metadata-Version: 2.1
Name: glitter-sdk
Version: 2.0.0
Summary: Glitter Protocol is a blockchain based database and index engine for developing and hosting web3 applications in decentralized storage networks.
Author: Glitter Protocol
Author-email: ted@glitterprotocol.io
Requires-Python: >=3.8,<4.0
Classifier: Programming Language :: Python :: 3
Classifier: Programming Language :: Python :: 3.8
Classifier: Programming Language :: Python :: 3.9
Classifier: Programming Language :: Python :: 3.10
Classifier: Programming Language :: Python :: 3.11
Classifier: Programming Language :: Python :: 3.12
Classifier: Programming Language :: Python :: 3.13
Requires-Dist: aiohttp (>=3.9.3,<4.0.0)
Requires-Dist: attr (>=0.3.2,<0.4.0)
Requires-Dist: attrs (>=22.2.0,<23.0.0)
Requires-Dist: base58 (>=2.1.1,<3.0.0)
Requires-Dist: bech32 (>=1.2.0,<2.0.0)
Requires-Dist: betterproto (==2.0.0b4)
Requires-Dist: bip32utils (>=0.3.post4,<0.4)
Requires-Dist: boltons (>=23.0.0,<24.0.0)
Requires-Dist: coincurve (==19.0.1)
Requires-Dist: furl (>=2.1.3,<3.0.0)
Requires-Dist: glitter-proto (==2.0.4)
Requires-Dist: grpcio (>=1.66.2,<2.0.0)
Requires-Dist: mnemonic (>=0.20,<0.21)
Requires-Dist: nest-asyncio (>=1.5.6,<2.0.0)
Requires-Dist: pycryptodomex (>=3.17,<4.0)
Requires-Dist: requests (>=2.31.0,<3.0.0)
Requires-Dist: setuptools (>=67.7.0)
Requires-Dist: wrapt (>=1.15.0,<2.0.0)
